sorcha_community_utils/_version.py
sorcha_community_utils/activity/lsst_comet/LICENSE
sorcha_community_utils/activity/lsst_comet/__init__.py
sorcha_community_utils/activity/lsst_comet/lsst_comet_activity.py
sorcha_community_utils/activity/lsst_comet/model.py
sorcha_community_utils/activity/lsst_comet/phase.py
sorcha_community_utils/lightcurve/sinusoidal/sinusoidal_lightcurve.py
sorcha_community_utils-0.2.dist-info/METADATA
sorcha_community_utils-0.2.dist-info/WHEEL
sorcha_community_utils-0.2.dist-info/top_level.txt
sorcha_community_utils-0.2.dist-info/RECORD
