Metadata-Version: 2.1
Name: sorcha-community-utils
Version: 0.2
Author-email: Meg Schwamb <m.schwamb@qub.ac.uk>
Classifier: Development Status :: 4 - Beta
Classifier: Intended Audience :: Developers
Classifier: Intended Audience :: Science/Research
Classifier: Operating System :: OS Independent
Classifier: Programming Language :: Python
Requires-Dist: pandas
Requires-Dist: numpy
Requires-Dist: sorcha
Requires-Dist: astropy
Requires-Dist: scipy
Provides-Extra: dev
Requires-Dist: pytest ; extra == 'dev'
Requires-Dist: pytest-cov ; extra == 'dev'
Requires-Dist: pre-commit ; extra == 'dev'
Requires-Dist: sphinx ==6.1.3 ; extra == 'dev'
Requires-Dist: sphinx-rtd-theme ==1.2.0 ; extra == 'dev'
Requires-Dist: sphinx-autoapi ==2.0.1 ; extra == 'dev'
Requires-Dist: black ; extra == 'dev'
Requires-Dist: nbconvert ; extra == 'dev'
Requires-Dist: nbsphinx ; extra == 'dev'
Requires-Dist: ipython ; extra == 'dev'
Requires-Dist: matplotlib ; extra == 'dev'
Requires-Dist: numpy ; extra == 'dev'
